python_clack/__init__.py
python_clack/_demo.py
python_clack/group.py
python_clack/log.py
python_clack/messages.py
python_clack/prompts.py
python_clack/spinner.py
python_clack/style.py
python_clack/symbols.py
python_clack/_core/__init__.py
python_clack/_core/prompt.py
python_clack/_core/render.py
python_clack/_core/state.py
python_clack/_demos/__init__.py
python_clack/_demos/config_builder.py
python_clack/_demos/form_wizard.py
python_clack/_demos/progress_demo.py
python_clack/_demos/quick_tour.py
python_clack/_demos/validation.py
python_clack/_prompts/__init__.py
python_clack/_prompts/confirm.py
python_clack/_prompts/multiselect.py
python_clack/_prompts/password.py
python_clack/_prompts/select.py
python_clack/_prompts/text.py
python_clack-0.1.2.dist-info/METADATA
python_clack-0.1.2.dist-info/WHEEL
python_clack-0.1.2.dist-info/entry_points.txt
python_clack-0.1.2.dist-info/licenses/LICENSE
python_clack-0.1.2.dist-info/RECORD
