Metadata-Version: 2.4
Name: python-clack
Version: 0.1.2
Summary: Beautiful CLI prompts for Python, inspired by clack
Project-URL: Homepage, https://github.com/oharu121/python-clack
Project-URL: Repository, https://github.com/oharu121/python-clack
License-Expression: MIT
License-File: LICENSE
Keywords: cli,interactive,prompts,terminal,tui
Classifier: Development Status :: 3 - Alpha
Classifier: Environment :: Console
Classifier: Intended Audience :: Developers
Classifier: License :: OSI Approved :: MIT License
Classifier: Programming Language :: Python :: 3.12
Classifier: Programming Language :: Python :: 3.13
Classifier: Topic :: Software Development :: Libraries :: Python Modules
Classifier: Typing :: Typed
Requires-Python: >=3.12
Requires-Dist: prompt-toolkit>=3.0.0
Requires-Dist: rich>=13.0.0
